isd_s3/__init__.py
isd_s3/__main__.py
isd_s3/config.py
isd_s3/isd_s3.py
ncar_isd_s3-1.1.2.dist-info/LICENSE
ncar_isd_s3-1.1.2.dist-info/METADATA
ncar_isd_s3-1.1.2.dist-info/WHEEL
ncar_isd_s3-1.1.2.dist-info/entry_points.txt
ncar_isd_s3-1.1.2.dist-info/top_level.txt
ncar_isd_s3-1.1.2.dist-info/RECORD
