Metadata-Version: 2.1
Name: ncar-isd-s3
Version: 1.1.2
Summary: NCAR ISD S3 object storage utility
Home-page: https://github.com/NCAR/isd-s3
Author: NCAR RDA Team
Author-email: rdahelp@ucar.edu
Classifier: Development Status :: 3 - Alpha
Classifier: License :: OSI Approved :: MIT License
Classifier: Operating System :: POSIX
Classifier: Programming Language :: Python :: 3
Classifier: Programming Language :: Python :: 3.4
Classifier: Programming Language :: Python :: 3.5
Classifier: Programming Language :: Python :: 3.6
Classifier: Programming Language :: Python :: 3.7
Classifier: Topic :: Software Development :: Libraries :: Python Modules
Classifier: Intended Audience :: Developers
Requires-Python: >=3.1
License-File: LICENSE
Requires-Dist: boto3
Requires-Dist: botocore
